MANIFEST.in
README.md
setup.py
humilis_kinesis_proxy/__init__.py
humilis_kinesis_proxy/meta.yaml.j2
humilis_kinesis_proxy/outputs.yaml.j2
humilis_kinesis_proxy/plugin.py
humilis_kinesis_proxy/resources.yaml.j2
humilis_kinesis_proxy.egg-info/PKG-INFO
humilis_kinesis_proxy.egg-info/SOURCES.txt
humilis_kinesis_proxy.egg-info/dependency_links.txt
humilis_kinesis_proxy.egg-info/entry_points.txt
humilis_kinesis_proxy.egg-info/not-zip-safe
humilis_kinesis_proxy.egg-info/requires.txt
humilis_kinesis_proxy.egg-info/top_level.txt