Metadata-Version: 1.1
Name: humilis-kinesis-proxy
Version: 0.2.6
Summary: Humilis plug-in to deploy a Lambda kinesis_proxy
Home-page: https://github.com/humilis/humilis-kinesis_proxy
Author: German Gomez-Herrero, FindHotel BV
Author-email: german@findhotel.net
License: MIT
Platform: UNKNOWN
Classifier: Programming Language :: Python :: 3
